abi2solc/__init__.py
abi2solc/main.py
abi2solc-0.1.0.dist-info/LICENSE
abi2solc-0.1.0.dist-info/METADATA
abi2solc-0.1.0.dist-info/WHEEL
abi2solc-0.1.0.dist-info/top_level.txt
abi2solc-0.1.0.dist-info/RECORD
