Metadata-Version: 2.1
Name: abi2solc
Version: 0.1.0
Summary: A library for generating Solidity interfaces from ABIs.
Home-page: https://github.com/iamdefinitelyahuman/abi2solc
Author: Ben Hauser
Author-email: b.hauser@zerolaw.tech
License: MIT
Keywords: ethereum,solidity,solc,abi
Platform: UNKNOWN
Classifier: Development Status :: 3 - Alpha
Classifier: Intended Audience :: Developers
Classifier: License :: OSI Approved :: MIT License
Classifier: Natural Language :: English
Classifier: Programming Language :: Python :: 3
Classifier: Programming Language :: Python :: 3.6
Classifier: Programming Language :: Python :: 3.7
Requires-Python: >=3.6, <4
